<annotation>
	<folder>train</folder>
	<filename>IMG_20210123_164108.jpg</filename>
	<path>C:\tensorflow1\models\research\object_detection\images\train\IMG_20210123_164108.jpg</path>
	<source>
		<database>Unknown</database>
	</source>
	<size>
		<width>2208</width>
		<height>4608</height>
		<depth>3</depth>
	</size>
	<segmented>0</segmented>
	<object>
		<name>nine</name>
		<pose>Unspecified</pose>
		<truncated>1</truncated>
		<difficult>0</difficult>
		<bndbox>
			<xmin>7</xmin>
			<ymin>1253</ymin>
			<xmax>2208</xmax>
			<ymax>3684</ymax>
		</bndbox>
	</object>
</annotation>
